stac_validator/__init__.py
stac_validator/stac_validator.py
stac_validator/utilities.py
stac_validator/validate.py
stac_validator-3.10.2.dist-info/licenses/LICENSE
stac_validator-3.10.2.dist-info/METADATA
stac_validator-3.10.2.dist-info/WHEEL
stac_validator-3.10.2.dist-info/entry_points.txt
stac_validator-3.10.2.dist-info/top_level.txt
stac_validator-3.10.2.dist-info/RECORD
