Metadata-Version: 2.4
Name: stac_validator
Version: 3.10.2
Summary: A package to validate STAC files
Author: James Banting
Author-email: Jonathan Healy <jonathan.d.healy@gmail.com>
License: Apache-2.0
Project-URL: Homepage, https://github.com/stac-utils/stac-validator
Project-URL: Repository, https://github.com/stac-utils/stac-validator
Keywords: STAC,validation,raster
Classifier: Intended Audience :: Information Technology
Classifier: Intended Audience :: Science/Research
Classifier: License :: OSI Approved :: Apache Software License
Classifier: Programming Language :: Python :: 3.8
Classifier: Topic :: Scientific/Engineering :: GIS
Requires-Python: >=3.8
License-File: LICENSE
Requires-Dist: requests>=2.32.3
Requires-Dist: jsonschema>=4.23.0
Requires-Dist: click>=8.1.8
Requires-Dist: referencing>=0.35.1
Requires-Dist: pyYAML>=6.0.1
Provides-Extra: dev
Requires-Dist: black; extra == "dev"
Requires-Dist: pytest; extra == "dev"
Requires-Dist: pytest-mypy; extra == "dev"
Requires-Dist: pre-commit; extra == "dev"
Requires-Dist: requests-mock; extra == "dev"
Requires-Dist: types-setuptools; extra == "dev"
Requires-Dist: stac-pydantic>=3.3.0; extra == "dev"
Requires-Dist: mypy; extra == "dev"
Requires-Dist: types-attrs; extra == "dev"
Requires-Dist: types-requests; extra == "dev"
Requires-Dist: types-jsonschema; extra == "dev"
Provides-Extra: pydantic
Requires-Dist: stac-pydantic>=3.3.0; extra == "pydantic"
Dynamic: license-file
